pyess/__init__.py
pyess/aio_ess.py
pyess/cli.py
pyess/constants.py
pyess/ess.py
pyess/essmqtt.py
pyess-0.1.23.dist-info/METADATA
pyess-0.1.23.dist-info/WHEEL
pyess-0.1.23.dist-info/entry_points.txt
pyess-0.1.23.dist-info/top_level.txt
pyess-0.1.23.dist-info/RECORD
