Metadata-Version: 2.2
Name: pyess
Version: 0.1.23
Summary: A small example package
Author-email: gluap <pypi@pgoergen.de>
License: MIT
Project-URL: Homepage, https://github.com/gluap/pyess
Project-URL: Issues, https://github.com/gluap/pyess/issues
Classifier: Development Status :: 3 - Alpha
Classifier: License :: OSI Approved :: MIT License
Classifier: Programming Language :: Python :: 3.7
Classifier: Programming Language :: Python :: 3.8
Classifier: Operating System :: OS Independent
Requires-Python: >=3.10
Requires-Dist: zeroconf
Requires-Dist: requests
Requires-Dist: graphyte
Requires-Dist: aiohttp
Requires-Dist: aiomqtt<2,>=0.4.0
Requires-Dist: ConfigArgParse
Provides-Extra: test
Requires-Dist: tox; extra == "test"
Requires-Dist: pytest; extra == "test"
